SMARTSEARCHCHATBOT/__init__.py
SMARTSEARCHCHATBOT/semantic_search_chatBot.py
SMARTSEARCHCHATBOT/semantic_search_chatBot_v2.py
smart_search_chatBot-0.1.9.dist-info/LICENSE
smart_search_chatBot-0.1.9.dist-info/METADATA
smart_search_chatBot-0.1.9.dist-info/WHEEL
smart_search_chatBot-0.1.9.dist-info/top_level.txt
smart_search_chatBot-0.1.9.dist-info/RECORD
