Metadata-Version: 2.1
Name: smart-search-chatBot
Version: 0.1.9
Summary: A package for semantic search using SentenceTransformers and Google Translate.
Home-page: https://github.com/yourusername/smart_search
Author: Abohassan&Abdelkader
Author-email: mohamed.ah.abohassan@gmail.com,abdelkadertalaat@gmail.com
Classifier: Programming Language :: Python :: 3
Classifier: License :: OSI Approved :: MIT License
Classifier: Operating System :: OS Independent
Requires-Python: >=3.6
License-File: LICENSE
Requires-Dist: pandas
Requires-Dist: sentence-transformers
Requires-Dist: googletrans (==4.0.0-rc1)
Requires-Dist: torch
Requires-Dist: transformers
